PyDocSmith/__init__.py
PyDocSmith/attrdoc.py
PyDocSmith/common.py
PyDocSmith/epydoc.py
PyDocSmith/google.py
PyDocSmith/numpydoc.py
PyDocSmith/parser.py
PyDocSmith/py.typed
PyDocSmith/rest.py
PyDocSmith/util.py
PyDocSmith/tests/__init__.py
PyDocSmith/tests/_pydoctor.py
PyDocSmith/tests/test_epydoc.py
PyDocSmith/tests/test_google.py
PyDocSmith/tests/test_numpydoc.py
PyDocSmith/tests/test_parse_from_object.py
PyDocSmith/tests/test_parser.py
PyDocSmith/tests/test_rest.py
PyDocSmith/tests/test_util.py
PyDocSmith-0.1.5.dist-info/LICENSE.md
PyDocSmith-0.1.5.dist-info/METADATA
PyDocSmith-0.1.5.dist-info/WHEEL
PyDocSmith-0.1.5.dist-info/top_level.txt
PyDocSmith-0.1.5.dist-info/RECORD
