Metadata-Version: 2.1
Name: PyDocSmith
Version: 0.1.5
Summary: It parses and composes docstrings in Google, Numpydoc, ReST and Epydoc.
Home-page: https://github.com/SingularityX-ai/PyDocSmith
Author: Suman Saurabh
Author-email: ss.sumansaurabh92@gmail.com
Classifier: Programming Language :: Python :: 3
Classifier: License :: OSI Approved :: MIT License
Classifier: Operating System :: OS Independent
Requires-Python: >=3.6
License-File: LICENSE.md
